limited_aiogram/__init__.py
limited_aiogram/limit_caller.py
limited_aiogram/limited_bot.py
limited_aiogram-1.0.2.dist-info/LICENSE
limited_aiogram-1.0.2.dist-info/METADATA
limited_aiogram-1.0.2.dist-info/WHEEL
limited_aiogram-1.0.2.dist-info/top_level.txt
limited_aiogram-1.0.2.dist-info/RECORD
