Metadata-Version: 2.1
Name: limited_aiogram
Version: 1.0.2
Summary: Limit your api calls to avoid  "Flood control exceeded"
Author: chazovtema
Author-email: chazovtema@mail.ru
Project-URL: github, https://github.com/chazovtema/limited_aiogram
Keywords: aiogram,limit
Classifier: Programming Language :: Python :: 3.10
Classifier: License :: OSI Approved :: MIT License
Classifier: Operating System :: OS Independent
Requires-Python: >=3.10
License-File: LICENSE
Requires-Dist: requests >=2.25.1
Requires-Dist: aiogram >=3.0.0
Requires-Dist: limiter >=0.3.1
Requires-Dist: cachetools >=5.3.2
